pyspark_iomete/__init__.py
pyspark_iomete/test_utils.py
pyspark_iomete/utils.py
pyspark_iomete-0.0.3.dist-info/METADATA
pyspark_iomete-0.0.3.dist-info/WHEEL
pyspark_iomete-0.0.3.dist-info/top_level.txt
pyspark_iomete-0.0.3.dist-info/RECORD
