Metadata-Version: 2.1
Name: pyspark-iomete
Version: 0.0.3
Summary: IOMETE's PySpark library that contains useful utilities for working with PySpark
Home-page: https://github.com/iomete/pyspark-iomete
Author: IOMETE
Author-email: vusal@iomete.com
License: Apache License 2.0
Keywords: iomete,pyspark,utils
Classifier: Development Status :: 5 - Production/Stable
Classifier: Topic :: Software Development :: Build Tools
Classifier: License :: OSI Approved :: Apache Software License
Classifier: Operating System :: Microsoft :: Windows
Classifier: Operating System :: MacOS :: MacOS X
Classifier: Operating System :: POSIX :: Linux
Classifier: Programming Language :: Python :: 3.7
Classifier: Programming Language :: Python :: 3.8
Classifier: Programming Language :: Python :: 3.9
Requires-Python: >=3.7
Provides-Extra: dev
Requires-Dist: pyspark ; extra == 'dev'
